{
  "autoupdate": {
    "url": "https://github.com/ryanoasis/nerd-fonts/releases/download/v$version/ProggyClean.zip"
  },
  "checkver": "github",
  "hash": "cf98665e543bc47bf669baaecd573b9ba35184b21c69bbe6e04450c7fb3ffbf2",
  "homepage": "https://github.com/ryanoasis/nerd-fonts",
  "installer": {
    "script": [
      "$AccessRule = New-Object System.Security.AccessControl.FileSystemAccessRule(\"NT AUTHORITY\\LOCAL SERVICE\", \"ReadAndExecute, Synchronize\", \"ContainerInherit, ObjectInherit\", \"None\", \"Allow\")",
      "$Acl = Get-Acl $dir",
      "$Acl.SetAccessRule($AccessRule)",
      "Set-Acl -Path $dir -AclObject $Acl",
      "$TargetKey = \"HKCU:\\SOFTWARE\\Microsoft\\Windows NT\\CurrentVersion\\Fonts\\Scoop.ProggyClean-NF-User\"",
      "New-Item -Path $TargetKey -Force | Out-Null",
      "Get-ChildItem \"$dir/\" -Filter '*Windows Compatible.*' | ForEach-Object {",
      "    New-ItemProperty -Path $TargetKey -Name $_.Name -Value $_.FullName -Force | Out-Null",
      "}"
    ]
  },
  "license": "MIT",
  "uninstaller": {
    "script": [
      "Remove-Item -Path \"HKCU:\\SOFTWARE\\Microsoft\\Windows NT\\CurrentVersion\\Fonts\\Scoop.ProggyClean-NF-User\""
    ]
  },
  "url": "https://github.com/ryanoasis/nerd-fonts/releases/download/v2.0.0/ProggyClean.zip",
  "version": "2.0.0"
}